migrations/0001_initial.py
migrations/__init__.py
sso_client/__init__.py
sso_client/apps.py
sso_client/backends.py
sso_client/middleware.py
sso_client/models.py
sso_client/send_message_to_rabbit.py
sso_client/migrations/0001_initial.py
sso_client/migrations/__init__.py
sso_client/services/__init__.py
sso_client/services/get_token_by_refresh.py
sso_client/services/get_user_info.py
kodland_sso_client-0.2.2.dist-info/LICENSE
kodland_sso_client-0.2.2.dist-info/METADATA
kodland_sso_client-0.2.2.dist-info/WHEEL
kodland_sso_client-0.2.2.dist-info/top_level.txt
kodland_sso_client-0.2.2.dist-info/RECORD
