Metadata-Version: 2.1
Name: kodland-sso-client
Version: 0.2.2
Summary: Django sso client package for Kodland
Home-page: UNKNOWN
Author: Dmitry Shoytov
Author-email: shoytov@gmail.com
License: UNKNOWN
Platform: UNKNOWN
Classifier: Programming Language :: Python :: 3
Classifier: License :: OSI Approved :: MIT License
Classifier: Operating System :: OS Independent
Requires-Python: >=3.6
Requires-Dist: django (>=3.0.1)
Requires-Dist: pyjwt (>=2.0.1)
Requires-Dist: requests (>=2.25.1)
Requires-Dist: pika (>=1.2.0)
